{
  "id": "G1",
  "children": [
    {
      "id": "N1",
      "labels": [
        {
          "text": "SetVariable2",
          "id": "L1",
          "width": 74.0,
          "height": 15.0
        }
      ],
      "ports": [
        {
          "id": "P1",
          "properties": {
            "port.side": "WEST",
            "port.index": "0"
          },
          "width": 8.0,
          "height": 8.0
        },
        {
          "id": "P2",
          "properties": {
            "port.side": "EAST",
            "port.index": "1"
          },
          "width": 8.0,
          "height": 8.0
        }
      ],
      "properties": {
        "portConstraints": "FIXED_ORDER",
        "nodeLabels.placement": "[H_LEFT, V_TOP, OUTSIDE]"
      },
      "width": 61.0,
      "height": 41.0
    },
    {
      "id": "N2",
      "labels": [
        {
          "text": "AddSubtract",
          "id": "L2",
          "width": 72.0,
          "height": 15.0
        }
      ],
      "ports": [
        {
          "id": "P3",
          "properties": {
            "port.side": "WEST",
            "port.index": "0"
          },
          "width": 8.0,
          "height": 8.0
        },
        {
          "id": "P4",
          "properties": {
            "port.side": "WEST",
            "port.index": "-1"
          },
          "width": 8.0,
          "height": 8.0
        },
        {
          "id": "P5",
          "properties": {
            "port.side": "EAST",
            "port.index": "2"
          },
          "width": 8.0,
          "height": 8.0
        }
      ],
      "properties": {
        "portConstraints": "FIXED_ORDER",
        "nodeLabels.placement": "[H_LEFT, V_TOP, OUTSIDE]"
      },
      "width": 41.0,
      "height": 41.0
    },
    {
      "id": "N3",
      "labels": [
        {
          "text": "Const",
          "id": "L3",
          "width": 34.0,
          "height": 15.0
        }
      ],
      "ports": [
        {
          "id": "P6",
          "properties": {
            "port.side": "EAST",
            "port.index": "0"
          },
          "width": 8.0,
          "height": 8.0
        },
        {
          "id": "P7",
          "properties": {
            "port.side": "WEST",
            "port.index": "-1"
          },
          "width": 8.0,
          "height": 8.0
        }
      ],
      "properties": {
        "portConstraints": "FIXED_ORDER",
        "nodeLabels.placement": "[H_LEFT, V_TOP, OUTSIDE]"
      },
      "width": 47.0,
      "height": 25.0
    },
    {
      "id": "N4",
      "labels": [
        {
          "text": "AddSubtract2",
          "id": "L4",
          "width": 80.0,
          "height": 15.0
        }
      ],
      "ports": [
        {
          "id": "P8",
          "properties": {
            "port.side": "WEST",
            "port.index": "0"
          },
          "width": 8.0,
          "height": 8.0
        },
        {
          "id": "P9",
          "properties": {
            "port.side": "WEST",
            "port.index": "-1"
          },
          "width": 8.0,
          "height": 8.0
        },
        {
          "id": "P10",
          "properties": {
            "port.side": "EAST",
            "port.index": "2"
          },
          "width": 8.0,
          "height": 8.0
        }
      ],
      "properties": {
        "portConstraints": "FIXED_ORDER",
        "nodeLabels.placement": "[H_LEFT, V_TOP, OUTSIDE]"
      },
      "width": 41.0,
      "height": 41.0
    },
    {
      "id": "N5",
      "labels": [
        {
          "text": "Expression",
          "id": "L5",
          "width": 66.0,
          "height": 15.0
        }
      ],
      "ports": [
        {
          "id": "P11",
          "properties": {
            "port.side": "EAST",
            "port.index": "0"
          },
          "width": 8.0,
          "height": 8.0
        },
        {
          "id": "P12",
          "properties": {
            "port.side": "WEST",
            "port.index": "-2"
          },
          "width": 8.0,
          "height": 8.0
        },
        {
          "id": "P13",
          "properties": {
            "port.side": "WEST",
            "port.index": "-3"
          },
          "width": 8.0,
          "height": 8.0
        }
      ],
      "properties": {
        "portConstraints": "FIXED_ORDER",
        "nodeLabels.placement": "[H_LEFT, V_TOP, OUTSIDE]"
      },
      "width": 37.0,
      "height": 25.0
    },
    {
      "id": "N6",
      "labels": [
        {
          "text": "BooleanSwitch",
          "id": "L6",
          "width": 87.0,
          "height": 15.0
        }
      ],
      "ports": [
        {
          "id": "P14",
          "properties": {
            "port.side": "WEST",
            "port.index": "0"
          },
          "width": 8.0,
          "height": 8.0
        },
        {
          "id": "P15",
          "properties": {
            "port.side": "SOUTH",
            "port.index": "-1"
          },
          "width": 8.0,
          "height": 8.0
        },
        {
          "id": "P16",
          "properties": {
            "port.side": "EAST",
            "port.index": "2"
          },
          "width": 8.0,
          "height": 8.0
        },
        {
          "id": "P17",
          "properties": {
            "port.side": "EAST",
            "port.index": "3"
          },
          "width": 8.0,
          "height": 8.0
        }
      ],
      "properties": {
        "portConstraints": "FIXED_ORDER",
        "nodeLabels.placement": "[H_LEFT, V_TOP, OUTSIDE]"
      },
      "width": 39.0,
      "height": 46.0
    },
    {
      "id": "N7",
      "labels": [
        {
          "text": "Expression2",
          "id": "L7",
          "width": 73.0,
          "height": 15.0
        }
      ],
      "ports": [
        {
          "id": "P18",
          "properties": {
            "port.side": "EAST",
            "port.index": "0"
          },
          "width": 8.0,
          "height": 8.0
        }
      ],
      "properties": {
        "portConstraints": "FIXED_ORDER",
        "nodeLabels.placement": "[H_LEFT, V_TOP, OUTSIDE]"
      },
      "width": 85.0,
      "height": 25.0
    },
    {
      "id": "N8",
      "labels": [
        {
          "text": "RecordDisassembler",
          "id": "L8",
          "width": 121.0,
          "height": 15.0
        }
      ],
      "ports": [
        {
          "id": "P19",
          "properties": {
            "port.side": "WEST",
            "port.index": "0"
          },
          "width": 8.0,
          "height": 8.0
        },
        {
          "id": "P20",
          "properties": {
            "port.side": "EAST",
            "port.index": "2"
          },
          "width": 8.0,
          "height": 8.0
        },
        {
          "id": "P21",
          "properties": {
            "port.side": "EAST",
            "port.index": "3"
          },
          "width": 8.0,
          "height": 8.0
        },
        {
          "id": "P22",
          "properties": {
            "port.side": "EAST",
            "port.index": "4"
          },
          "width": 8.0,
          "height": 8.0
        }
      ],
      "properties": {
        "portConstraints": "FIXED_ORDER",
        "nodeLabels.placement": "[H_LEFT, V_TOP, OUTSIDE]"
      },
      "width": 10.0,
      "height": 41.0
    },
    {
      "id": "N9",
      "labels": [
        {
          "text": "Equals",
          "id": "L9",
          "width": 40.0,
          "height": 15.0
        }
      ],
      "ports": [
        {
          "id": "P23",
          "properties": {
            "port.side": "WEST",
            "port.index": "0"
          },
          "width": 8.0,
          "height": 8.0
        },
        {
          "id": "P24",
          "properties": {
            "port.side": "EAST",
            "port.index": "1"
          },
          "width": 8.0,
          "height": 8.0
        }
      ],
      "properties": {
        "portConstraints": "FIXED_ORDER",
        "nodeLabels.placement": "[H_LEFT, V_TOP, OUTSIDE]"
      },
      "width": 61.0,
      "height": 31.0
    },
    {
      "id": "N10",
      "labels": [
        {
          "text": "Clock",
          "id": "L10",
          "width": 33.0,
          "height": 15.0
        }
      ],
      "ports": [
        {
          "id": "P25",
          "properties": {
            "port.side": "EAST",
            "port.index": "0"
          },
          "width": 8.0,
          "height": 8.0
        },
        {
          "id": "P26",
          "properties": {
            "port.side": "WEST",
            "port.index": "-1"
          },
          "width": 8.0,
          "height": 8.0
        },
        {
          "id": "P27",
          "properties": {
            "port.side": "WEST",
            "port.index": "-2"
          },
          "width": 8.0,
          "height": 8.0
        }
      ],
      "properties": {
        "portConstraints": "FIXED_ORDER",
        "nodeLabels.placement": "[H_LEFT, V_TOP, OUTSIDE]"
      },
      "width": 41.0,
      "height": 41.0
    },
    {
      "id": "N11",
      "labels": [
        {
          "text": "SetVariable",
          "id": "L11",
          "width": 67.0,
          "height": 15.0
        }
      ],
      "ports": [
        {
          "id": "P28",
          "properties": {
            "port.side": "WEST",
            "port.index": "0"
          },
          "width": 8.0,
          "height": 8.0
        },
        {
          "id": "P29",
          "properties": {
            "port.side": "EAST",
            "port.index": "1"
          },
          "width": 8.0,
          "height": 8.0
        }
      ],
      "properties": {
        "portConstraints": "FIXED_ORDER",
        "nodeLabels.placement": "[H_LEFT, V_TOP, OUTSIDE]"
      },
      "width": 61.0,
      "height": 41.0
    },
    {
      "id": "N12",
      "labels": [
        {
          "text": "Ramp",
          "id": "L12",
          "width": 35.0,
          "height": 15.0
        }
      ],
      "ports": [
        {
          "id": "P30",
          "properties": {
            "port.side": "EAST",
            "port.index": "0"
          },
          "width": 8.0,
          "height": 8.0
        },
        {
          "id": "P31",
          "properties": {
            "port.side": "WEST",
            "port.index": "-1"
          },
          "width": 8.0,
          "height": 8.0
        },
        {
          "id": "P32",
          "properties": {
            "port.side": "WEST",
            "port.index": "-2"
          },
          "width": 8.0,
          "height": 8.0
        }
      ],
      "properties": {
        "portConstraints": "FIXED_ORDER",
        "nodeLabels.placement": "[H_LEFT, V_TOP, OUTSIDE]"
      },
      "width": 61.0,
      "height": 41.0
    },
    {
      "id": "N13",
      "labels": [
        {
          "text": "Ramp2",
          "id": "L13",
          "width": 42.0,
          "height": 15.0
        }
      ],
      "ports": [
        {
          "id": "P33",
          "properties": {
            "port.side": "EAST",
            "port.index": "0"
          },
          "width": 8.0,
          "height": 8.0
        },
        {
          "id": "P34",
          "properties": {
            "port.side": "WEST",
            "port.index": "-1"
          },
          "width": 8.0,
          "height": 8.0
        },
        {
          "id": "P35",
          "properties": {
            "port.side": "WEST",
            "port.index": "-2"
          },
          "width": 8.0,
          "height": 8.0
        }
      ],
      "properties": {
        "portConstraints": "FIXED_ORDER",
        "nodeLabels.placement": "[H_LEFT, V_TOP, OUTSIDE]"
      },
      "width": 61.0,
      "height": 41.0
    },
    {
      "id": "N14",
      "labels": [
        {
          "text": "Expression2",
          "id": "L14",
          "width": 73.0,
          "height": 15.0
        }
      ],
      "ports": [
        {
          "id": "P36",
          "properties": {
            "port.side": "EAST",
            "port.index": "0"
          },
          "width": 8.0,
          "height": 8.0
        },
        {
          "id": "P37",
          "properties": {
            "port.side": "WEST",
            "port.index": "-2"
          },
          "width": 8.0,
          "height": 8.0
        }
      ],
      "properties": {
        "portConstraints": "FIXED_ORDER",
        "nodeLabels.placement": "[H_LEFT, V_TOP, OUTSIDE]"
      },
      "width": 32.0,
      "height": 25.0
    },
    {
      "id": "N15",
      "labels": [
        {
          "text": "Expression3",
          "id": "L15",
          "width": 73.0,
          "height": 15.0
        }
      ],
      "ports": [
        {
          "id": "P38",
          "properties": {
            "port.side": "EAST",
            "port.index": "0"
          },
          "width": 8.0,
          "height": 8.0
        },
        {
          "id": "P39",
          "properties": {
            "port.side": "WEST",
            "port.index": "-2"
          },
          "width": 8.0,
          "height": 8.0
        }
      ],
      "properties": {
        "portConstraints": "FIXED_ORDER",
        "nodeLabels.placement": "[H_LEFT, V_TOP, OUTSIDE]"
      },
      "width": 37.0,
      "height": 25.0
    },
    {
      "id": "N16",
      "labels": [
        {
          "text": "Expression",
          "id": "L16",
          "width": 66.0,
          "height": 15.0
        }
      ],
      "ports": [
        {
          "id": "P40",
          "properties": {
            "port.side": "EAST",
            "port.index": "0"
          },
          "width": 8.0,
          "height": 8.0
        },
        {
          "id": "P41",
          "properties": {
            "port.side": "WEST",
            "port.index": "-2"
          },
          "width": 8.0,
          "height": 8.0
        },
        {
          "id": "P42",
          "properties": {
            "port.side": "WEST",
            "port.index": "-3"
          },
          "width": 8.0,
          "height": 8.0
        }
      ],
      "properties": {
        "portConstraints": "FIXED_ORDER",
        "nodeLabels.placement": "[H_LEFT, V_TOP, OUTSIDE]"
      },
      "width": 37.0,
      "height": 25.0
    },
    {
      "id": "N17",
      "labels": [
        {
          "text": "Const",
          "id": "L17",
          "width": 34.0,
          "height": 15.0
        }
      ],
      "ports": [
        {
          "id": "P43",
          "properties": {
            "port.side": "EAST",
            "port.index": "0"
          },
          "width": 8.0,
          "height": 8.0
        },
        {
          "id": "P44",
          "properties": {
            "port.side": "WEST",
            "port.index": "-1"
          },
          "width": 8.0,
          "height": 8.0
        }
      ],
      "properties": {
        "portConstraints": "FIXED_ORDER",
        "nodeLabels.placement": "[H_LEFT, V_TOP, OUTSIDE]"
      },
      "width": 21.0,
      "height": 25.0
    },
    {
      "id": "N18",
      "labels": [
        {
          "text": "RecordAssembler",
          "id": "L18",
          "width": 104.0,
          "height": 15.0
        }
      ],
      "ports": [
        {
          "id": "P45",
          "properties": {
            "port.side": "EAST",
            "port.index": "0"
          },
          "width": 8.0,
          "height": 8.0
        },
        {
          "id": "P46",
          "properties": {
            "port.side": "WEST",
            "port.index": "-2"
          },
          "width": 8.0,
          "height": 8.0
        },
        {
          "id": "P47",
          "properties": {
            "port.side": "WEST",
            "port.index": "-3"
          },
          "width": 8.0,
          "height": 8.0
        },
        {
          "id": "P48",
          "properties": {
            "port.side": "WEST",
            "port.index": "-4"
          },
          "width": 8.0,
          "height": 8.0
        }
      ],
      "properties": {
        "portConstraints": "FIXED_ORDER",
        "nodeLabels.placement": "[H_LEFT, V_TOP, OUTSIDE]"
      },
      "width": 10.0,
      "height": 41.0
    },
    {
      "id": "N19",
      "labels": [
        {
          "text": "SetVariable2",
          "id": "L19",
          "width": 74.0,
          "height": 15.0
        }
      ],
      "ports": [
        {
          "id": "P49",
          "properties": {
            "port.side": "WEST",
            "port.index": "0"
          },
          "width": 8.0,
          "height": 8.0
        },
        {
          "id": "P50",
          "properties": {
            "port.side": "EAST",
            "port.index": "1"
          },
          "width": 8.0,
          "height": 8.0
        }
      ],
      "properties": {
        "portConstraints": "FIXED_ORDER",
        "nodeLabels.placement": "[H_LEFT, V_TOP, OUTSIDE]"
      },
      "width": 61.0,
      "height": 41.0
    },
    {
      "id": "N20",
      "labels": [
        {
          "text": "AddSubtract",
          "id": "L20",
          "width": 72.0,
          "height": 15.0
        }
      ],
      "ports": [
        {
          "id": "P51",
          "properties": {
            "port.side": "WEST",
            "port.index": "0"
          },
          "width": 8.0,
          "height": 8.0
        },
        {
          "id": "P52",
          "properties": {
            "port.side": "WEST",
            "port.index": "-1"
          },
          "width": 8.0,
          "height": 8.0
        },
        {
          "id": "P53",
          "properties": {
            "port.side": "EAST",
            "port.index": "2"
          },
          "width": 8.0,
          "height": 8.0
        }
      ],
      "properties": {
        "portConstraints": "FIXED_ORDER",
        "nodeLabels.placement": "[H_LEFT, V_TOP, OUTSIDE]"
      },
      "width": 41.0,
      "height": 41.0
    },
    {
      "id": "N21",
      "labels": [
        {
          "text": "Const",
          "id": "L21",
          "width": 34.0,
          "height": 15.0
        }
      ],
      "ports": [
        {
          "id": "P54",
          "properties": {
            "port.side": "EAST",
            "port.index": "0"
          },
          "width": 8.0,
          "height": 8.0
        },
        {
          "id": "P55",
          "properties": {
            "port.side": "WEST",
            "port.index": "-1"
          },
          "width": 8.0,
          "height": 8.0
        }
      ],
      "properties": {
        "portConstraints": "FIXED_ORDER",
        "nodeLabels.placement": "[H_LEFT, V_TOP, OUTSIDE]"
      },
      "width": 43.0,
      "height": 25.0
    },
    {
      "id": "N22",
      "labels": [
        {
          "text": "AddSubtract2",
          "id": "L22",
          "width": 80.0,
          "height": 15.0
        }
      ],
      "ports": [
        {
          "id": "P56",
          "properties": {
            "port.side": "WEST",
            "port.index": "0"
          },
          "width": 8.0,
          "height": 8.0
        },
        {
          "id": "P57",
          "properties": {
            "port.side": "WEST",
            "port.index": "-1"
          },
          "width": 8.0,
          "height": 8.0
        },
        {
          "id": "P58",
          "properties": {
            "port.side": "EAST",
            "port.index": "2"
          },
          "width": 8.0,
          "height": 8.0
        }
      ],
      "properties": {
        "portConstraints": "FIXED_ORDER",
        "nodeLabels.placement": "[H_LEFT, V_TOP, OUTSIDE]"
      },
      "width": 41.0,
      "height": 41.0
    },
    {
      "id": "N23",
      "labels": [
        {
          "text": "Expression",
          "id": "L23",
          "width": 66.0,
          "height": 15.0
        }
      ],
      "ports": [
        {
          "id": "P59",
          "properties": {
            "port.side": "EAST",
            "port.index": "0"
          },
          "width": 8.0,
          "height": 8.0
        },
        {
          "id": "P60",
          "properties": {
            "port.side": "WEST",
            "port.index": "-2"
          },
          "width": 8.0,
          "height": 8.0
        },
        {
          "id": "P61",
          "properties": {
            "port.side": "WEST",
            "port.index": "-3"
          },
          "width": 8.0,
          "height": 8.0
        }
      ],
      "properties": {
        "portConstraints": "FIXED_ORDER",
        "nodeLabels.placement": "[H_LEFT, V_TOP, OUTSIDE]"
      },
      "width": 37.0,
      "height": 25.0
    },
    {
      "id": "N24",
      "labels": [
        {
          "text": "BooleanSwitch",
          "id": "L24",
          "width": 87.0,
          "height": 15.0
        }
      ],
      "ports": [
        {
          "id": "P62",
          "properties": {
            "port.side": "WEST",
            "port.index": "0"
          },
          "width": 8.0,
          "height": 8.0
        },
        {
          "id": "P63",
          "properties": {
            "port.side": "SOUTH",
            "port.index": "-1"
          },
          "width": 8.0,
          "height": 8.0
        },
        {
          "id": "P64",
          "properties": {
            "port.side": "EAST",
            "port.index": "2"
          },
          "width": 8.0,
          "height": 8.0
        },
        {
          "id": "P65",
          "properties": {
            "port.side": "EAST",
            "port.index": "3"
          },
          "width": 8.0,
          "height": 8.0
        }
      ],
      "properties": {
        "portConstraints": "FIXED_ORDER",
        "nodeLabels.placement": "[H_LEFT, V_TOP, OUTSIDE]"
      },
      "width": 39.0,
      "height": 46.0
    },
    {
      "id": "N25",
      "labels": [
        {
          "text": "Expression2",
          "id": "L25",
          "width": 73.0,
          "height": 15.0
        }
      ],
      "ports": [
        {
          "id": "P66",
          "properties": {
            "port.side": "EAST",
            "port.index": "0"
          },
          "width": 8.0,
          "height": 8.0
        }
      ],
      "properties": {
        "portConstraints": "FIXED_ORDER",
        "nodeLabels.placement": "[H_LEFT, V_TOP, OUTSIDE]"
      },
      "width": 85.0,
      "height": 25.0
    },
    {
      "id": "N26",
      "labels": [
        {
          "text": "RecordDisassembler",
          "id": "L26",
          "width": 121.0,
          "height": 15.0
        }
      ],
      "ports": [
        {
          "id": "P67",
          "properties": {
            "port.side": "WEST",
            "port.index": "0"
          },
          "width": 8.0,
          "height": 8.0
        },
        {
          "id": "P68",
          "properties": {
            "port.side": "EAST",
            "port.index": "2"
          },
          "width": 8.0,
          "height": 8.0
        },
        {
          "id": "P69",
          "properties": {
            "port.side": "EAST",
            "port.index": "3"
          },
          "width": 8.0,
          "height": 8.0
        },
        {
          "id": "P70",
          "properties": {
            "port.side": "EAST",
            "port.index": "4"
          },
          "width": 8.0,
          "height": 8.0
        }
      ],
      "properties": {
        "portConstraints": "FIXED_ORDER",
        "nodeLabels.placement": "[H_LEFT, V_TOP, OUTSIDE]"
      },
      "width": 10.0,
      "height": 41.0
    },
    {
      "id": "N27",
      "labels": [
        {
          "text": "Equals",
          "id": "L27",
          "width": 40.0,
          "height": 15.0
        }
      ],
      "ports": [
        {
          "id": "P71",
          "properties": {
            "port.side": "WEST",
            "port.index": "0"
          },
          "width": 8.0,
          "height": 8.0
        },
        {
          "id": "P72",
          "properties": {
            "port.side": "EAST",
            "port.index": "1"
          },
          "width": 8.0,
          "height": 8.0
        }
      ],
      "properties": {
        "portConstraints": "FIXED_ORDER",
        "nodeLabels.placement": "[H_LEFT, V_TOP, OUTSIDE]"
      },
      "width": 61.0,
      "height": 31.0
    },
    {
      "id": "N28",
      "labels": [
        {
          "text": "Display2",
          "id": "L28",
          "width": 51.0,
          "height": 15.0
        }
      ],
      "ports": [
        {
          "id": "P73",
          "properties": {
            "port.side": "WEST",
            "port.index": "0"
          },
          "width": 8.0,
          "height": 8.0
        }
      ],
      "properties": {
        "portConstraints": "FIXED_ORDER",
        "nodeLabels.placement": "[H_LEFT, V_TOP, OUTSIDE]"
      },
      "width": 41.0,
      "height": 31.0
    },
    {
      "id": "N29",
      "labels": [
        {
          "text": "SetVariable2",
          "id": "L29",
          "width": 74.0,
          "height": 15.0
        }
      ],
      "ports": [
        {
          "id": "P74",
          "properties": {
            "port.side": "WEST",
            "port.index": "0"
          },
          "width": 8.0,
          "height": 8.0
        },
        {
          "id": "P75",
          "properties": {
            "port.side": "EAST",
            "port.index": "1"
          },
          "width": 8.0,
          "height": 8.0
        }
      ],
      "properties": {
        "portConstraints": "FIXED_ORDER",
        "nodeLabels.placement": "[H_LEFT, V_TOP, OUTSIDE]"
      },
      "width": 61.0,
      "height": 41.0
    },
    {
      "id": "N30",
      "labels": [
        {
          "text": "AddSubtract",
          "id": "L30",
          "width": 72.0,
          "height": 15.0
        }
      ],
      "ports": [
        {
          "id": "P76",
          "properties": {
            "port.side": "WEST",
            "port.index": "0"
          },
          "width": 8.0,
          "height": 8.0
        },
        {
          "id": "P77",
          "properties": {
            "port.side": "WEST",
            "port.index": "-1"
          },
          "width": 8.0,
          "height": 8.0
        },
        {
          "id": "P78",
          "properties": {
            "port.side": "EAST",
            "port.index": "2"
          },
          "width": 8.0,
          "height": 8.0
        }
      ],
      "properties": {
        "portConstraints": "FIXED_ORDER",
        "nodeLabels.placement": "[H_LEFT, V_TOP, OUTSIDE]"
      },
      "width": 41.0,
      "height": 41.0
    },
    {
      "id": "N31",
      "labels": [
        {
          "text": "Const",
          "id": "L31",
          "width": 34.0,
          "height": 15.0
        }
      ],
      "ports": [
        {
          "id": "P79",
          "properties": {
            "port.side": "EAST",
            "port.index": "0"
          },
          "width": 8.0,
          "height": 8.0
        },
        {
          "id": "P80",
          "properties": {
            "port.side": "WEST",
            "port.index": "-1"
          },
          "width": 8.0,
          "height": 8.0
        }
      ],
      "properties": {
        "portConstraints": "FIXED_ORDER",
        "nodeLabels.placement": "[H_LEFT, V_TOP, OUTSIDE]"
      },
      "width": 47.0,
      "height": 25.0
    },
    {
      "id": "N32",
      "labels": [
        {
          "text": "AddSubtract2",
          "id": "L32",
          "width": 80.0,
          "height": 15.0
        }
      ],
      "ports": [
        {
          "id": "P81",
          "properties": {
            "port.side": "WEST",
            "port.index": "0"
          },
          "width": 8.0,
          "height": 8.0
        },
        {
          "id": "P82",
          "properties": {
            "port.side": "WEST",
            "port.index": "-1"
          },
          "width": 8.0,
          "height": 8.0
        },
        {
          "id": "P83",
          "properties": {
            "port.side": "EAST",
            "port.index": "2"
          },
          "width": 8.0,
          "height": 8.0
        }
      ],
      "properties": {
        "portConstraints": "FIXED_ORDER",
        "nodeLabels.placement": "[H_LEFT, V_TOP, OUTSIDE]"
      },
      "width": 41.0,
      "height": 41.0
    },
    {
      "id": "N33",
      "labels": [
        {
          "text": "Expression",
          "id": "L33",
          "width": 66.0,
          "height": 15.0
        }
      ],
      "ports": [
        {
          "id": "P84",
          "properties": {
            "port.side": "EAST",
            "port.index": "0"
          },
          "width": 8.0,
          "height": 8.0
        },
        {
          "id": "P85",
          "properties": {
            "port.side": "WEST",
            "port.index": "-2"
          },
          "width": 8.0,
          "height": 8.0
        },
        {
          "id": "P86",
          "properties": {
            "port.side": "WEST",
            "port.index": "-3"
          },
          "width": 8.0,
          "height": 8.0
        }
      ],
      "properties": {
        "portConstraints": "FIXED_ORDER",
        "nodeLabels.placement": "[H_LEFT, V_TOP, OUTSIDE]"
      },
      "width": 37.0,
      "height": 25.0
    },
    {
      "id": "N34",
      "labels": [
        {
          "text": "BooleanSwitch",
          "id": "L34",
          "width": 87.0,
          "height": 15.0
        }
      ],
      "ports": [
        {
          "id": "P87",
          "properties": {
            "port.side": "WEST",
            "port.index": "0"
          },
          "width": 8.0,
          "height": 8.0
        },
        {
          "id": "P88",
          "properties": {
            "port.side": "SOUTH",
            "port.index": "-1"
          },
          "width": 8.0,
          "height": 8.0
        },
        {
          "id": "P89",
          "properties": {
            "port.side": "EAST",
            "port.index": "2"
          },
          "width": 8.0,
          "height": 8.0
        },
        {
          "id": "P90",
          "properties": {
            "port.side": "EAST",
            "port.index": "3"
          },
          "width": 8.0,
          "height": 8.0
        }
      ],
      "properties": {
        "portConstraints": "FIXED_ORDER",
        "nodeLabels.placement": "[H_LEFT, V_TOP, OUTSIDE]"
      },
      "width": 39.0,
      "height": 46.0
    },
    {
      "id": "N35",
      "labels": [
        {
          "text": "Expression2",
          "id": "L35",
          "width": 73.0,
          "height": 15.0
        }
      ],
      "ports": [
        {
          "id": "P91",
          "properties": {
            "port.side": "EAST",
            "port.index": "0"
          },
          "width": 8.0,
          "height": 8.0
        }
      ],
      "properties": {
        "portConstraints": "FIXED_ORDER",
        "nodeLabels.placement": "[H_LEFT, V_TOP, OUTSIDE]"
      },
      "width": 85.0,
      "height": 25.0
    },
    {
      "id": "N36",
      "labels": [
        {
          "text": "RecordDisassembler",
          "id": "L36",
          "width": 121.0,
          "height": 15.0
        }
      ],
      "ports": [
        {
          "id": "P92",
          "properties": {
            "port.side": "WEST",
            "port.index": "0"
          },
          "width": 8.0,
          "height": 8.0
        },
        {
          "id": "P93",
          "properties": {
            "port.side": "EAST",
            "port.index": "2"
          },
          "width": 8.0,
          "height": 8.0
        },
        {
          "id": "P94",
          "properties": {
            "port.side": "EAST",
            "port.index": "3"
          },
          "width": 8.0,
          "height": 8.0
        },
        {
          "id": "P95",
          "properties": {
            "port.side": "EAST",
            "port.index": "4"
          },
          "width": 8.0,
          "height": 8.0
        }
      ],
      "properties": {
        "portConstraints": "FIXED_ORDER",
        "nodeLabels.placement": "[H_LEFT, V_TOP, OUTSIDE]"
      },
      "width": 10.0,
      "height": 41.0
    },
    {
      "id": "N37",
      "labels": [
        {
          "text": "Equals",
          "id": "L37",
          "width": 40.0,
          "height": 15.0
        }
      ],
      "ports": [
        {
          "id": "P96",
          "properties": {
            "port.side": "WEST",
            "port.index": "0"
          },
          "width": 8.0,
          "height": 8.0
        },
        {
          "id": "P97",
          "properties": {
            "port.side": "EAST",
            "port.index": "1"
          },
          "width": 8.0,
          "height": 8.0
        }
      ],
      "properties": {
        "portConstraints": "FIXED_ORDER",
        "nodeLabels.placement": "[H_LEFT, V_TOP, OUTSIDE]"
      },
      "width": 61.0,
      "height": 31.0
    },
    {
      "id": "N38",
      "labels": [
        {
          "text": "Clock",
          "id": "L38",
          "width": 33.0,
          "height": 15.0
        }
      ],
      "ports": [
        {
          "id": "P98",
          "properties": {
            "port.side": "EAST",
            "port.index": "0"
          },
          "width": 8.0,
          "height": 8.0
        },
        {
          "id": "P99",
          "properties": {
            "port.side": "WEST",
            "port.index": "-1"
          },
          "width": 8.0,
          "height": 8.0
        },
        {
          "id": "P100",
          "properties": {
            "port.side": "WEST",
            "port.index": "-2"
          },
          "width": 8.0,
          "height": 8.0
        }
      ],
      "properties": {
        "portConstraints": "FIXED_ORDER",
        "nodeLabels.placement": "[H_LEFT, V_TOP, OUTSIDE]"
      },
      "width": 41.0,
      "height": 41.0
    },
    {
      "id": "N39",
      "labels": [
        {
          "text": "SetVariable",
          "id": "L39",
          "width": 67.0,
          "height": 15.0
        }
      ],
      "ports": [
        {
          "id": "P101",
          "properties": {
            "port.side": "WEST",
            "port.index": "0"
          },
          "width": 8.0,
          "height": 8.0
        },
        {
          "id": "P102",
          "properties": {
            "port.side": "EAST",
            "port.index": "1"
          },
          "width": 8.0,
          "height": 8.0
        }
      ],
      "properties": {
        "portConstraints": "FIXED_ORDER",
        "nodeLabels.placement": "[H_LEFT, V_TOP, OUTSIDE]"
      },
      "width": 61.0,
      "height": 41.0
    },
    {
      "id": "N40",
      "labels": [
        {
          "text": "Ramp",
          "id": "L40",
          "width": 35.0,
          "height": 15.0
        }
      ],
      "ports": [
        {
          "id": "P103",
          "properties": {
            "port.side": "EAST",
            "port.index": "0"
          },
          "width": 8.0,
          "height": 8.0
        },
        {
          "id": "P104",
          "properties": {
            "port.side": "WEST",
            "port.index": "-1"
          },
          "width": 8.0,
          "height": 8.0
        },
        {
          "id": "P105",
          "properties": {
            "port.side": "WEST",
            "port.index": "-2"
          },
          "width": 8.0,
          "height": 8.0
        }
      ],
      "properties": {
        "portConstraints": "FIXED_ORDER",
        "nodeLabels.placement": "[H_LEFT, V_TOP, OUTSIDE]"
      },
      "width": 61.0,
      "height": 41.0
    },
    {
      "id": "N41",
      "labels": [
        {
          "text": "Ramp2",
          "id": "L41",
          "width": 42.0,
          "height": 15.0
        }
      ],
      "ports": [
        {
          "id": "P106",
          "properties": {
            "port.side": "EAST",
            "port.index": "0"
          },
          "width": 8.0,
          "height": 8.0
        },
        {
          "id": "P107",
          "properties": {
            "port.side": "WEST",
            "port.index": "-1"
          },
          "width": 8.0,
          "height": 8.0
        },
        {
          "id": "P108",
          "properties": {
            "port.side": "WEST",
            "port.index": "-2"
          },
          "width": 8.0,
          "height": 8.0
        }
      ],
      "properties": {
        "portConstraints": "FIXED_ORDER",
        "nodeLabels.placement": "[H_LEFT, V_TOP, OUTSIDE]"
      },
      "width": 61.0,
      "height": 41.0
    },
    {
      "id": "N42",
      "labels": [
        {
          "text": "Expression2",
          "id": "L42",
          "width": 73.0,
          "height": 15.0
        }
      ],
      "ports": [
        {
          "id": "P109",
          "properties": {
            "port.side": "EAST",
            "port.index": "0"
          },
          "width": 8.0,
          "height": 8.0
        },
        {
          "id": "P110",
          "properties": {
            "port.side": "WEST",
            "port.index": "-2"
          },
          "width": 8.0,
          "height": 8.0
        }
      ],
      "properties": {
        "portConstraints": "FIXED_ORDER",
        "nodeLabels.placement": "[H_LEFT, V_TOP, OUTSIDE]"
      },
      "width": 32.0,
      "height": 25.0
    },
    {
      "id": "N43",
      "labels": [
        {
          "text": "Expression3",
          "id": "L43",
          "width": 73.0,
          "height": 15.0
        }
      ],
      "ports": [
        {
          "id": "P111",
          "properties": {
            "port.side": "EAST",
            "port.index": "0"
          },
          "width": 8.0,
          "height": 8.0
        },
        {
          "id": "P112",
          "properties": {
            "port.side": "WEST",
            "port.index": "-2"
          },
          "width": 8.0,
          "height": 8.0
        }
      ],
      "properties": {
        "portConstraints": "FIXED_ORDER",
        "nodeLabels.placement": "[H_LEFT, V_TOP, OUTSIDE]"
      },
      "width": 37.0,
      "height": 25.0
    },
    {
      "id": "N44",
      "labels": [
        {
          "text": "Expression",
          "id": "L44",
          "width": 66.0,
          "height": 15.0
        }
      ],
      "ports": [
        {
          "id": "P113",
          "properties": {
            "port.side": "EAST",
            "port.index": "0"
          },
          "width": 8.0,
          "height": 8.0
        },
        {
          "id": "P114",
          "properties": {
            "port.side": "WEST",
            "port.index": "-2"
          },
          "width": 8.0,
          "height": 8.0
        },
        {
          "id": "P115",
          "properties": {
            "port.side": "WEST",
            "port.index": "-3"
          },
          "width": 8.0,
          "height": 8.0
        }
      ],
      "properties": {
        "portConstraints": "FIXED_ORDER",
        "nodeLabels.placement": "[H_LEFT, V_TOP, OUTSIDE]"
      },
      "width": 37.0,
      "height": 25.0
    },
    {
      "id": "N45",
      "labels": [
        {
          "text": "Const",
          "id": "L45",
          "width": 34.0,
          "height": 15.0
        }
      ],
      "ports": [
        {
          "id": "P116",
          "properties": {
            "port.side": "EAST",
            "port.index": "0"
          },
          "width": 8.0,
          "height": 8.0
        },
        {
          "id": "P117",
          "properties": {
            "port.side": "WEST",
            "port.index": "-1"
          },
          "width": 8.0,
          "height": 8.0
        }
      ],
      "properties": {
        "portConstraints": "FIXED_ORDER",
        "nodeLabels.placement": "[H_LEFT, V_TOP, OUTSIDE]"
      },
      "width": 21.0,
      "height": 25.0
    },
    {
      "id": "N46",
      "labels": [
        {
          "text": "RecordAssembler",
          "id": "L46",
          "width": 104.0,
          "height": 15.0
        }
      ],
      "ports": [
        {
          "id": "P118",
          "properties": {
            "port.side": "EAST",
            "port.index": "0"
          },
          "width": 8.0,
          "height": 8.0
        },
        {
          "id": "P119",
          "properties": {
            "port.side": "WEST",
            "port.index": "-2"
          },
          "width": 8.0,
          "height": 8.0
        },
        {
          "id": "P120",
          "properties": {
            "port.side": "WEST",
            "port.index": "-3"
          },
          "width": 8.0,
          "height": 8.0
        },
        {
          "id": "P121",
          "properties": {
            "port.side": "WEST",
            "port.index": "-4"
          },
          "width": 8.0,
          "height": 8.0
        }
      ],
      "properties": {
        "portConstraints": "FIXED_ORDER",
        "nodeLabels.placement": "[H_LEFT, V_TOP, OUTSIDE]"
      },
      "width": 10.0,
      "height": 41.0
    }
  ],
  "properties": {
    "portConstraints": "FREE"
  },
  "edges": [
    {
      "id": "E1",
      "sources": [
        "P5"
      ],
      "targets": [
        "P12"
      ]
    },
    {
      "id": "E2",
      "sources": [
        "P6"
      ],
      "targets": [
        "P3"
      ]
    },
    {
      "id": "E3",
      "sources": [
        "P6"
      ],
      "targets": [
        "P8"
      ]
    },
    {
      "id": "E4",
      "sources": [
        "P10"
      ],
      "targets": [
        "P13"
      ]
    },
    {
      "id": "E5",
      "sources": [
        "P11"
      ],
      "targets": [
        "P14"
      ]
    },
    {
      "id": "E6",
      "sources": [
        "P16"
      ],
      "targets": [
        "P1"
      ]
    },
    {
      "id": "E7",
      "sources": [
        "P18"
      ],
      "targets": [
        "P23"
      ]
    },
    {
      "id": "E8",
      "sources": [
        "P20"
      ],
      "targets": [
        "P3"
      ]
    },
    {
      "id": "E9",
      "sources": [
        "P21"
      ],
      "targets": [
        "P8"
      ]
    },
    {
      "id": "E10",
      "sources": [
        "P22"
      ],
      "targets": [
        "P23"
      ]
    },
    {
      "id": "E11",
      "sources": [
        "P24"
      ],
      "targets": [
        "P15"
      ]
    },
    {
      "id": "E12",
      "sources": [
        "P25"
      ],
      "targets": [
        "P31"
      ]
    },
    {
      "id": "E13",
      "sources": [
        "P25"
      ],
      "targets": [
        "P34"
      ]
    },
    {
      "id": "E14",
      "sources": [
        "P25"
      ],
      "targets": [
        "P44"
      ]
    },
    {
      "id": "E15",
      "sources": [
        "P30"
      ],
      "targets": [
        "P37"
      ]
    },
    {
      "id": "E16",
      "sources": [
        "P33"
      ],
      "targets": [
        "P39"
      ]
    },
    {
      "id": "E17",
      "sources": [
        "P36"
      ],
      "targets": [
        "P42"
      ]
    },
    {
      "id": "E18",
      "sources": [
        "P36"
      ],
      "targets": [
        "P47"
      ]
    },
    {
      "id": "E19",
      "sources": [
        "P38"
      ],
      "targets": [
        "P41"
      ]
    },
    {
      "id": "E20",
      "sources": [
        "P38"
      ],
      "targets": [
        "P46"
      ]
    },
    {
      "id": "E21",
      "sources": [
        "P40"
      ],
      "targets": [
        "P28"
      ]
    },
    {
      "id": "E22",
      "sources": [
        "P43"
      ],
      "targets": [
        "P48"
      ]
    },
    {
      "id": "E23",
      "sources": [
        "P53"
      ],
      "targets": [
        "P60"
      ]
    },
    {
      "id": "E24",
      "sources": [
        "P54"
      ],
      "targets": [
        "P51"
      ]
    },
    {
      "id": "E25",
      "sources": [
        "P54"
      ],
      "targets": [
        "P56"
      ]
    },
    {
      "id": "E26",
      "sources": [
        "P58"
      ],
      "targets": [
        "P61"
      ]
    },
    {
      "id": "E27",
      "sources": [
        "P59"
      ],
      "targets": [
        "P62"
      ]
    },
    {
      "id": "E28",
      "sources": [
        "P59"
      ],
      "targets": [
        "P73"
      ]
    },
    {
      "id": "E29",
      "sources": [
        "P64"
      ],
      "targets": [
        "P49"
      ]
    },
    {
      "id": "E30",
      "sources": [
        "P66"
      ],
      "targets": [
        "P71"
      ]
    },
    {
      "id": "E31",
      "sources": [
        "P68"
      ],
      "targets": [
        "P51"
      ]
    },
    {
      "id": "E32",
      "sources": [
        "P69"
      ],
      "targets": [
        "P56"
      ]
    },
    {
      "id": "E33",
      "sources": [
        "P70"
      ],
      "targets": [
        "P71"
      ]
    },
    {
      "id": "E34",
      "sources": [
        "P72"
      ],
      "targets": [
        "P63"
      ]
    },
    {
      "id": "E35",
      "sources": [
        "P78"
      ],
      "targets": [
        "P85"
      ]
    },
    {
      "id": "E36",
      "sources": [
        "P79"
      ],
      "targets": [
        "P76"
      ]
    },
    {
      "id": "E37",
      "sources": [
        "P79"
      ],
      "targets": [
        "P81"
      ]
    },
    {
      "id": "E38",
      "sources": [
        "P83"
      ],
      "targets": [
        "P86"
      ]
    },
    {
      "id": "E39",
      "sources": [
        "P84"
      ],
      "targets": [
        "P87"
      ]
    },
    {
      "id": "E40",
      "sources": [
        "P89"
      ],
      "targets": [
        "P74"
      ]
    },
    {
      "id": "E41",
      "sources": [
        "P91"
      ],
      "targets": [
        "P96"
      ]
    },
    {
      "id": "E42",
      "sources": [
        "P93"
      ],
      "targets": [
        "P76"
      ]
    },
    {
      "id": "E43",
      "sources": [
        "P94"
      ],
      "targets": [
        "P81"
      ]
    },
    {
      "id": "E44",
      "sources": [
        "P95"
      ],
      "targets": [
        "P96"
      ]
    },
    {
      "id": "E45",
      "sources": [
        "P97"
      ],
      "targets": [
        "P88"
      ]
    },
    {
      "id": "E46",
      "sources": [
        "P98"
      ],
      "targets": [
        "P104"
      ]
    },
    {
      "id": "E47",
      "sources": [
        "P98"
      ],
      "targets": [
        "P107"
      ]
    },
    {
      "id": "E48",
      "sources": [
        "P98"
      ],
      "targets": [
        "P117"
      ]
    },
    {
      "id": "E49",
      "sources": [
        "P103"
      ],
      "targets": [
        "P110"
      ]
    },
    {
      "id": "E50",
      "sources": [
        "P106"
      ],
      "targets": [
        "P112"
      ]
    },
    {
      "id": "E51",
      "sources": [
        "P109"
      ],
      "targets": [
        "P115"
      ]
    },
    {
      "id": "E52",
      "sources": [
        "P109"
      ],
      "targets": [
        "P120"
      ]
    },
    {
      "id": "E53",
      "sources": [
        "P111"
      ],
      "targets": [
        "P114"
      ]
    },
    {
      "id": "E54",
      "sources": [
        "P111"
      ],
      "targets": [
        "P119"
      ]
    },
    {
      "id": "E55",
      "sources": [
        "P113"
      ],
      "targets": [
        "P101"
      ]
    },
    {
      "id": "E56",
      "sources": [
        "P116"
      ],
      "targets": [
        "P121"
      ]
    }
  ]
}